yo/__init__.py
yo/__main__.py
yo/api.py
yo/main.py
yo/oci.py
yo/ssh.py
yo/subc.py
yo/tasks.py
yo/util.py
yo/data/pkgman
yo/data/sample.yo.ini
yo/data/yo_tasklib.sh
yo/data/yo-tasks/drgn
yo/data/yo-tasks/ocid
yo/data/yo-tasks/test-deps
yo/data/yo-tasks/test-existing-task
yo/data/yo-tasks/test-run-many
yo/data/yo-tasks/test-task
yo-1.11.1.dist-info/LICENSE.txt
yo-1.11.1.dist-info/METADATA
yo-1.11.1.dist-info/THIRD_PARTY_LICENSES.txt
yo-1.11.1.dist-info/WHEEL
yo-1.11.1.dist-info/entry_points.txt
yo-1.11.1.dist-info/top_level.txt
yo-1.11.1.dist-info/RECORD
