Metadata-Version: 2.1
Name: yo
Version: 1.11.1
Summary: A fast and simple CLI client for managing OCI instances
Home-page: https://github.com/oracle/yo
Author: Oracle
Author-email: stephen.s.brennan@oracle.com
License: UPL
Keywords: oci client
Classifier: Programming Language :: Python :: 3
Classifier: License :: OSI Approved :: Universal Permissive License (UPL)
Classifier: Development Status :: 5 - Production/Stable
Classifier: Natural Language :: English
License-File: LICENSE.txt
License-File: THIRD_PARTY_LICENSES.txt
Requires-Dist: rich >=12.3.0
Requires-Dist: oci >=2.85.0
Requires-Dist: setuptools
Requires-Dist: argcomplete
